README.txt
setup.py
twistmc.py
twistmc.egg-info/PKG-INFO
twistmc.egg-info/SOURCES.txt
twistmc.egg-info/dependency_links.txt
twistmc.egg-info/requires.txt
twistmc.egg-info/top_level.txt