Metadata-Version: 1.0
Name: twistmc
Version: 0.1.3
Summary: Twist My Components!
Home-page: https://github.com/kaiyou/twistmc
Author: Pierre Jaury
Author-email: pierre@jaury.eu
License: GPLv3
Platform: UNKNOWN
